{
  "tiers": [
    {"rank": 1, "maxHeight": 0.05, "maxFontSize": 5.0, "maxRocketSize": 8.0},
    {"rank": 2, "maxHeight": 0.06, "maxFontSize": 4.8, "maxRocketSize": 7.8},
    {"rank": 3, "maxHeight": 0.07, "maxFontSize": 4.6, "maxRocketSize": 7.6},
    {"rank": 4, "maxHeight": 0.08, "maxFontSize": 4.4, "maxRocketSize": 7.4},
    {"rank": 5, "maxHeight": 0.09, "maxFontSize": 4.2, "maxRocketSize": 7.2},
    {"rank": 6, "maxHeight": 0.10, "maxFontSize": 4.0, "maxRocketSize": 7.0},
    {"rank": 7, "maxHeight": 0.11, "maxFontSize": 3.9, "maxRocketSize": 6.8},
    {"rank": 8, "maxHeight": 0.12, "maxFontSize": 3.8, "maxRocketSize": 6.6},
    {"rank": 9, "maxHeight": 0.13, "maxFontSize": 3.7, "maxRocketSize": 6.4},
    {"rank": 10, "maxHeight": 0.14, "maxFontSize": 3.6, "maxRocketSize": 6.2},
    {"rank": 11, "maxHeight": 0.15, "maxFontSize": 3.5, "maxRocketSize": 6.0},
    {"rank": 12, "maxHeight": 0.16, "maxFontSize": 3.4, "maxRocketSize": 5.8},
    {"rank": 13, "maxHeight": 0.17, "maxFontSize": 3.3, "maxRocketSize": 5.6},
    {"rank": 14, "maxHeight": 0.18, "maxFontSize": 3.2, "maxRocketSize": 5.4},
    {"rank": 15, "maxHeight": 0.19, "maxFontSize": 3.1, "maxRocketSize": 5.2},
    {"rank": 16, "maxHeight": 0.20, "maxFontSize": 3.0, "maxRocketSize": 5.0},
    {"rank": 17, "maxHeight": 0.21, "maxFontSize": 2.9, "maxRocketSize": 4.8},
    {"rank": 18, "maxHeight": 0.22, "maxFontSize": 2.8, "maxRocketSize": 4.6},
    {"rank": 19, "maxHeight": 0.23, "maxFontSize": 2.7, "maxRocketSize": 4.4},
    {"rank": 20, "maxHeight": 0.24, "maxFontSize": 2.6, "maxRocketSize": 4.2},
    {"rank": 21, "maxHeight": 0.25, "maxFontSize": 2.5, "maxRocketSize": 4.0},
    {"rank": 22, "maxHeight": 0.26, "maxFontSize": 2.4, "maxRocketSize": 3.9},
    {"rank": 23, "maxHeight": 0.27, "maxFontSize": 0.3, "maxRocketSize": 0.8},
    {"rank": 24, "maxHeight": 0.28, "maxFontSize": 2.2, "maxRocketSize": 3.7},
    {"rank": 25, "maxHeight": 0.29, "maxFontSize": 2.1, "maxRocketSize": 3.6},
    {"rank": 26, "maxHeight": 0.30, "maxFontSize": 2.0, "maxRocketSize": 3.5},
    {"rank": 27, "maxHeight": 0.31, "maxFontSize": 1.95, "maxRocketSize": 3.4},
    {"rank": 28, "maxHeight": 0.32, "maxFontSize": 1.90, "maxRocketSize": 3.3},
    {"rank": 29, "maxHeight": 0.33, "maxFontSize": 1.85, "maxRocketSize": 3.2},
    {"rank": 30, "maxHeight": 0.34, "maxFontSize": 1.80, "maxRocketSize": 3.1},
    {"rank": 31, "maxHeight": 0.35, "maxFontSize": 1.75, "maxRocketSize": 3.0},
    {"rank": 32, "maxHeight": 0.36, "maxFontSize": 1.70, "maxRocketSize": 2.9},
    {"rank": 33, "maxHeight": 0.37, "maxFontSize": 1.65, "maxRocketSize": 2.8},
    {"rank": 34, "maxHeight": 0.38, "maxFontSize": 1.60, "maxRocketSize": 2.7},
    {"rank": 35, "maxHeight": 0.39, "maxFontSize": 1.55, "maxRocketSize": 2.6},
    {"rank": 36, "maxHeight": 0.40, "maxFontSize": 1.50, "maxRocketSize": 2.5},
    {"rank": 37, "maxHeight": 0.41, "maxFontSize": 1.45, "maxRocketSize": 2.4},
    {"rank": 38, "maxHeight": 0.42, "maxFontSize": 1.40, "maxRocketSize": 2.3},
    {"rank": 39, "maxHeight": 0.43, "maxFontSize": 1.35, "maxRocketSize": 2.2},
    {"rank": 40, "maxHeight": 0.44, "maxFontSize": 1.30, "maxRocketSize": 2.1},
    {"rank": 41, "maxHeight": 0.45, "maxFontSize": 1.25, "maxRocketSize": 2.0},
    {"rank": 42, "maxHeight": 0.46, "maxFontSize": 1.20, "maxRocketSize": 1.9},
    {"rank": 43, "maxHeight": 0.47, "maxFontSize": 1.15, "maxRocketSize": 1.8},
    {"rank": 44, "maxHeight": 0.48, "maxFontSize": 1.10, "maxRocketSize": 1.7},
    {"rank": 45, "maxHeight": 0.49, "maxFontSize": 1.05, "maxRocketSize": 1.6},
    {"rank": 46, "maxHeight": 0.50, "maxFontSize": 1.00, "maxRocketSize": 1.5},
    {"rank": 47, "maxHeight": 0.51, "maxFontSize": 0.95, "maxRocketSize": 1.4},
    {"rank": 48, "maxHeight": 0.52, "maxFontSize": 0.90, "maxRocketSize": 1.3},
    {"rank": 49, "maxHeight": 0.53, "maxFontSize": 0.85, "maxRocketSize": 1.2},
    {"rank": 50, "maxHeight": 0.54, "maxFontSize": 0.80, "maxRocketSize": 1.1},
    {"rank": 51, "maxHeight": 0.55, "maxFontSize": 0.75, "maxRocketSize": 1.0},
    {"rank": 52, "maxHeight": 0.56, "maxFontSize": 0.70, "maxRocketSize": 0.9},
    {"rank": 53, "maxHeight": 0.57, "maxFontSize": 0.65, "maxRocketSize": 0.8},
    {"rank": 54, "maxHeight": 0.58, "maxFontSize": 0.60, "maxRocketSize": 0.7},
    {"rank": 55, "maxHeight": 0.59, "maxFontSize": 0.55, "maxRocketSize": 0.6},
    {"rank": 56, "maxHeight": 0.60, "maxFontSize": 0.50, "maxRocketSize": 0.5},
    {"rank": 57, "maxHeight": 0.61, "maxFontSize": 0.45, "maxRocketSize": 0.45},
    {"rank": 58, "maxHeight": 0.62, "maxFontSize": 0.40, "maxRocketSize": 0.40},
    {"rank": 59, "maxHeight": 0.63, "maxFontSize": 0.35, "maxRocketSize": 0.35},
    {"rank": 60, "maxHeight": 0.64, "maxFontSize": 0.30, "maxRocketSize": 0.30},
    {"rank": 61, "maxHeight": 0.65, "maxFontSize": 0.28, "maxRocketSize": 0.28},
    {"rank": 62, "maxHeight": 0.66, "maxFontSize": 0.26, "maxRocketSize": 0.26},
    {"rank": 63, "maxHeight": 0.67, "maxFontSize": 0.24, "maxRocketSize": 0.24},
    {"rank": 64, "maxHeight": 0.68, "maxFontSize": 0.22, "maxRocketSize": 0.22},
    {"rank": 65, "maxHeight": 0.69, "maxFontSize": 0.20, "maxRocketSize": 0.20},
    {"rank": 66, "maxHeight": 0.70, "maxFontSize": 0.19, "maxRocketSize": 0.19},
    {"rank": 67, "maxHeight": 0.71, "maxFontSize": 0.18, "maxRocketSize": 0.18},
    {"rank": 68, "maxHeight": 0.72, "maxFontSize": 0.17, "maxRocketSize": 0.17},
    {"rank": 69, "maxHeight": 0.73, "maxFontSize": 0.16, "maxRocketSize": 0.16},
    {"rank": 70, "maxHeight": 0.74, "maxFontSize": 0.15, "maxRocketSize": 0.15},
    {"rank": 71, "maxHeight": 0.75, "maxFontSize": 0.14, "maxRocketSize": 0.14},
    {"rank": 72, "maxHeight": 0.76, "maxFontSize": 0.13, "maxRocketSize": 0.13},
    {"rank": 73, "maxHeight": 0.77, "maxFontSize": 0.12, "maxRocketSize": 0.12},
    {"rank": 74, "maxHeight": 0.78, "maxFontSize": 0.11, "maxRocketSize": 0.11},
    {"rank": 75, "maxHeight": 0.79, "maxFontSize": 0.10, "maxRocketSize": 0.10},
    {"rank": 76, "maxHeight": 0.80, "maxFontSize": 0.095, "maxRocketSize": 0.095},
    {"rank": 77, "maxHeight": 0.81, "maxFontSize": 0.090, "maxRocketSize": 0.090},
    {"rank": 78, "maxHeight": 0.82, "maxFontSize": 0.085, "maxRocketSize": 0.085},
    {"rank": 79, "maxHeight": 0.83, "maxFontSize": 0.080, "maxRocketSize": 0.080},
    {"rank": 80, "maxHeight": 0.84, "maxFontSize": 0.075, "maxRocketSize": 0.075},
    {"rank": 81, "maxHeight": 0.85, "maxFontSize": 0.070, "maxRocketSize": 0.070},
    {"rank": 82, "maxHeight": 0.86, "maxFontSize": 0.065, "maxRocketSize": 0.065},
    {"rank": 83, "maxHeight": 0.87, "maxFontSize": 0.060, "maxRocketSize": 0.060},
    {"rank": 84, "maxHeight": 0.88, "maxFontSize": 0.055, "maxRocketSize": 0.055},
    {"rank": 85, "maxHeight": 0.89, "maxFontSize": 0.050, "maxRocketSize": 0.050},
    {"rank": 86, "maxHeight": 0.90, "maxFontSize": 0.045, "maxRocketSize": 0.045},
    {"rank": 87, "maxHeight": 0.91, "maxFontSize": 0.040, "maxRocketSize": 0.040},
    {"rank": 88, "maxHeight": 0.92, "maxFontSize": 0.035, "maxRocketSize": 0.035},
    {"rank": 89, "maxHeight": 0.93, "maxFontSize": 0.030, "maxRocketSize": 0.030},
    {"rank": 90, "maxHeight": 0.94, "maxFontSize": 0.025, "maxRocketSize": 0.025},
    {"rank": 91, "maxHeight": 0.95, "maxFontSize": 0.022, "maxRocketSize": 0.022},
    {"rank": 92, "maxHeight": 0.95, "maxFontSize": 0.020, "maxRocketSize": 0.020},
    {"rank": 93, "maxHeight": 0.95, "maxFontSize": 0.018, "maxRocketSize": 0.018},
    {"rank": 94, "maxHeight": 0.95, "maxFontSize": 0.016, "maxRocketSize": 0.016},
    {"rank": 95, "maxHeight": 0.95, "maxFontSize": 0.014, "maxRocketSize": 0.014},
    {"rank": 96, "maxHeight": 0.95, "maxFontSize": 0.012, "maxRocketSize": 0.012},
    {"rank": 97, "maxHeight": 0.95, "maxFontSize": 0.010, "maxRocketSize": 0.010},
    {"rank": 98, "maxHeight": 0.95, "maxFontSize": 0.009, "maxRocketSize": 0.009},
    {"rank": 99, "maxHeight": 0.95, "maxFontSize": 0.008, "maxRocketSize": 0.008},
    {"rank": 100, "maxHeight": 0.69, "maxFontSize": 0.40, "maxRocketSize": 0.40}
  ],
  "description": "Tier configuration for rocket fireworks. maxHeight: 0.0 (top of screen) to 1.0 (bottom), maxFontSize: text multiplier, maxRocketSize: explosion size multiplier"
}
